django_static_ionicons/__init__.py
django_static_ionicons/admin.py
django_static_ionicons/apps.py
django_static_ionicons/models.py
django_static_ionicons/tests.py
django_static_ionicons/views.py
django_static_ionicons/migrations/__init__.py
django_static_ionicons/static/ionicons/css/ionicons.css
django_static_ionicons/static/ionicons/css/ionicons.min.css
django_static_ionicons/static/ionicons/fonts/ionicons.eot
django_static_ionicons/static/ionicons/fonts/ionicons.svg
django_static_ionicons/static/ionicons/fonts/ionicons.ttf
django_static_ionicons/static/ionicons/fonts/ionicons.woff
django_static_ionicons-2.0.1.6.dist-info/licenses/LICENSE
django_static_ionicons-2.0.1.6.dist-info/METADATA
django_static_ionicons-2.0.1.6.dist-info/WHEEL
django_static_ionicons-2.0.1.6.dist-info/top_level.txt
django_static_ionicons-2.0.1.6.dist-info/RECORD
